epomakercontroller/__init__.py
epomakercontroller/__main__.py
epomakercontroller/cli.py
epomakercontroller/commands/EpomakerCommand.py
epomakercontroller/commands/EpomakerCpuCommand.py
epomakercontroller/commands/EpomakerImageCommand.py
epomakercontroller/commands/EpomakerKeyRGBCommand.py
epomakercontroller/commands/EpomakerProfileCommand.py
epomakercontroller/commands/EpomakerRemapKeysCommand.py
epomakercontroller/commands/EpomakerTempCommand.py
epomakercontroller/commands/EpomakerTimeCommand.py
epomakercontroller/commands/__init__.py
epomakercontroller/commands/data/__init__.py
epomakercontroller/commands/data/constants.py
epomakercontroller/commands/reports/Report.py
epomakercontroller/commands/reports/ReportWithData.py
epomakercontroller/commands/reports/__init__.py
epomakercontroller/configs/configs.py
epomakercontroller/configs/keymaps/EpomakerEP64.json
epomakercontroller/configs/keymaps/EpomakerRT100.json
epomakercontroller/configs/keymaps/GamakayTK68-HE.json
epomakercontroller/configs/layouts/EpomakerEP64.json
epomakercontroller/configs/layouts/EpomakerRT100-UK-ISO.json
epomakercontroller/configs/layouts/GamakayTK68-HE.json
epomakercontroller/epomaker_utils.py
epomakercontroller/epomakercontroller.py
epomakercontroller/keyboard_gui.py
epomakercontroller/keyboard_keys.py
epomakercontroller/py.typed
epomakercontroller-0.0.6.dist-info/METADATA
epomakercontroller-0.0.6.dist-info/WHEEL
epomakercontroller-0.0.6.dist-info/entry_points.txt
epomakercontroller-0.0.6.dist-info/RECORD
