Metadata-Version: 2.1
Name: EpomakerController
Version: 0.0.6
Summary: Epomakercontroller
Home-page: https://github.com/strodgers/EpomakerController
License: MIT
Author: Sam Rodgers
Author-email: samueltrodgers@duck.com
Requires-Python: >=3.9,<4.0
Classifier: License :: OSI Approved :: MIT License
Classifier: Programming Language :: Python :: 3
Classifier: Programming Language :: Python :: 3.9
Classifier: Programming Language :: Python :: 3.10
Classifier: Programming Language :: Python :: 3.11
Classifier: Programming Language :: Python :: 3.12
Requires-Dist: appdirs (==1.4.4)
Requires-Dist: click (>=8.0.1)
Requires-Dist: hidapi (==0.14.0)
Requires-Dist: numpy (<2.0)
Requires-Dist: opencv-python-headless (==4.10.0.82)
Requires-Dist: psutil (>=6.0.0)
Requires-Dist: python-dateutil (==2.8.2)
Project-URL: Changelog, https://github.com/strodgers/EpomakerController/releases
Project-URL: Documentation, https://EpomakerController.readthedocs.io
Project-URL: Repository, https://github.com/strodgers/EpomakerController
